simple_client_server/__init__.py
simple_client_server/client_server.py
simple_client_server/longer.py
simple_client_server-0.0.1.dist-info/LICENSE
simple_client_server-0.0.1.dist-info/WHEEL
simple_client_server-0.0.1.dist-info/METADATA
simple_client_server-0.0.1.dist-info/RECORD
