Metadata-Version: 2.1
Name: simple_client_server
Version: 0.0.1
Summary: Socket client and server using encryption.
Author-email: "John C. G. Sturdy" <jcg.sturdy@gmail.com>
Classifier: License :: OSI Approved :: GNU General Public License v3 or later (GPLv3+)
Requires-Dist: Crypto
